ApaDown/ApaDown.py
ApaDown/__init__.py
ApaDown/cli.py
ApaDown/download.py
ApaDown/get_downloadable_links.py
ApaDown-1.0.0.dist-info/METADATA
ApaDown-1.0.0.dist-info/WHEEL
ApaDown-1.0.0.dist-info/entry_points.txt
ApaDown-1.0.0.dist-info/top_level.txt
ApaDown-1.0.0.dist-info/RECORD
